marrow.mailer-4.0.3-py3.7-nspkg.pth
marrow/mailer/__init__.py
marrow/mailer/address.py
marrow/mailer/exc.py
marrow/mailer/logger.py
marrow/mailer/message.py
marrow/mailer/release.py
marrow/mailer/testing.py
marrow/mailer/validator.py
marrow/mailer/__pycache__/__init__.cpython-37.opt-1.pyc
marrow/mailer/__pycache__/address.cpython-37.opt-1.pyc
marrow/mailer/__pycache__/exc.cpython-37.opt-1.pyc
marrow/mailer/__pycache__/logger.cpython-37.opt-1.pyc
marrow/mailer/__pycache__/message.cpython-37.opt-1.pyc
marrow/mailer/__pycache__/release.cpython-37.opt-1.pyc
marrow/mailer/__pycache__/testing.cpython-37.opt-1.pyc
marrow/mailer/__pycache__/validator.cpython-37.opt-1.pyc
marrow/mailer/manager/__init__.py
marrow/mailer/manager/dynamic.py
marrow/mailer/manager/futures.py
marrow/mailer/manager/immediate.py
marrow/mailer/manager/transactional.py
marrow/mailer/manager/util.py
marrow/mailer/manager/__pycache__/__init__.cpython-37.opt-1.pyc
marrow/mailer/manager/__pycache__/dynamic.cpython-37.opt-1.pyc
marrow/mailer/manager/__pycache__/futures.cpython-37.opt-1.pyc
marrow/mailer/manager/__pycache__/immediate.cpython-37.opt-1.pyc
marrow/mailer/manager/__pycache__/transactional.cpython-37.opt-1.pyc
marrow/mailer/manager/__pycache__/util.cpython-37.opt-1.pyc
marrow/mailer/transport/__init__.py
marrow/mailer/transport/gae.py
marrow/mailer/transport/imap.py
marrow/mailer/transport/log.py
marrow/mailer/transport/maildir.py
marrow/mailer/transport/mailgun.py
marrow/mailer/transport/mbox.py
marrow/mailer/transport/mock.py
marrow/mailer/transport/postmark.py
marrow/mailer/transport/sendgrid.py
marrow/mailer/transport/sendmail.py
marrow/mailer/transport/ses.py
marrow/mailer/transport/smtp.py
marrow/mailer/transport/__pycache__/__init__.cpython-37.opt-1.pyc
marrow/mailer/transport/__pycache__/gae.cpython-37.opt-1.pyc
marrow/mailer/transport/__pycache__/imap.cpython-37.opt-1.pyc
marrow/mailer/transport/__pycache__/log.cpython-37.opt-1.pyc
marrow.mailer-4.0.3.dist-info/LICENSE.txt
marrow.mailer-4.0.3.dist-info/METADATA
marrow.mailer-4.0.3.dist-info/WHEEL
marrow.mailer-4.0.3.dist-info/entry_points.txt
marrow.mailer-4.0.3.dist-info/namespace_packages.txt
marrow.mailer-4.0.3.dist-info/top_level.txt
marrow.mailer-4.0.3.dist-info/RECORD
